pythonfrost/__init__.py
pythonfrost/response.py
pythonfrost/router.py
pythonfrost/server.py
pythonfrost/session.py
pythonfrost-0.1.1.2.dist-info/licenses/LICENSE
pythonfrost-0.1.1.2.dist-info/METADATA
pythonfrost-0.1.1.2.dist-info/WHEEL
pythonfrost-0.1.1.2.dist-info/top_level.txt
pythonfrost-0.1.1.2.dist-info/RECORD
