Metadata-Version: 2.4
Name: pythonfrost
Version: 0.1.1.2
Summary: A lightweight Python microframework for building fast and simple web apps.
Home-page: https://github.com/ZhiarPiroti/Frost-A-Lightweight-Easy-to-Use-Python-Microframework
Author: Zhiar Piroti
Author-email: zhiarsmp11@gmail.com
Classifier: Programming Language :: Python :: 3
Classifier: License :: OSI Approved :: MIT License
Classifier: Operating System :: OS Independent
Requires-Python: >=3.10
License-File: LICENSE
Dynamic: author
Dynamic: author-email
Dynamic: classifier
Dynamic: description
Dynamic: description-content-type
Dynamic: home-page
Dynamic: license-file
Dynamic: requires-python
Dynamic: summary
